[
  {
    "icon": "<img src='https://raw.githubusercontent.com/nabendudebnathbharatiya-bot/My-app-assets2/main/images/Chakra-ad/Gemini_Generated_Image_46ovu346ovu346ov.png' style='width:100%; height:100%; object-fit:cover;'>",
    "title": "কসমিক ভাইব্রেটর",
    "subtitle": "সম্পূর্ণ বিদ্যুৎবিহীন"
  },
  {
    "icon": "<img src='https://images.unsplash.com/photo-1516542076529-1ea3854896f2?auto=format&fit=crop&w=400&q=80' style='width:100%; height:100%; object-fit:cover;'>",
    "title": "এনার্জি ব্যালেন্সার",
    "subtitle": "জিরো এনার্জি প্রযুক্তি"
  },
  {
    "icon": "<img src='https://images.unsplash.com/photo-1519389950473-47ba0277781c?auto=format&fit=crop&w=400&q=80' style='width:100%; height:100%; object-fit:cover;'>",
    "title": "ম্যাগনেটিক হিলার",
    "subtitle": "প্রাকৃতিক নিরাময়"
  },
  {
    "icon": "<img src='https://images.unsplash.com/photo-1576091160550-217358c7c819?auto=format&fit=crop&w=400&q=80' style='width:100%; height:100%; object-fit:cover;'>",
    "title": "অরা স্ক্যানার",
    "subtitle": "অরা ডিটেকশন"
  }
]
